ibrx/__init__.py
ibrx/client.py
ibrx/test_app.py
ibrx-0.0.2.dist-info/LICENSE
ibrx-0.0.2.dist-info/METADATA
ibrx-0.0.2.dist-info/WHEEL
ibrx-0.0.2.dist-info/top_level.txt
ibrx-0.0.2.dist-info/RECORD
