Metadata-Version: 2.1
Name: ibrx
Version: 0.0.2
Summary: IB API using RxPY
Home-page: https://github.com/dayfine/ibapi-rxpy
Author: dayfine
Author-email: 
License: UNKNOWN
Platform: UNKNOWN
Classifier: Programming Language :: Python :: 3
Classifier: License :: OSI Approved :: Apache Software License
Classifier: Operating System :: OS Independent
Requires-Python: >=3.7
